complementizer/__init__.py
complementizer/complementizer.py
complementizer/form.py
complementizer/type.py
complementizer-1.2.2.dist-info/LICENSE
complementizer-1.2.2.dist-info/METADATA
complementizer-1.2.2.dist-info/WHEEL
complementizer-1.2.2.dist-info/top_level.txt
complementizer-1.2.2.dist-info/RECORD
