Metadata-Version: 2.1
Name: complementizer
Version: 1.2.2
Summary: Complementizer makes it easy to create and fill out automated forms for interactions with APIs.
Home-page: https://github.com/ismaelvguedes/Complementizer
Author: Ismael Guedes
Author-email: ismael.basic@gmail.com
Classifier: Programming Language :: Python :: 3
Classifier: License :: OSI Approved :: MIT License
Classifier: Operating System :: OS Independent
Requires-Python: >=3.6
License-File: LICENSE
Requires-Dist: requests
Requires-Dist: faker
